context_handler/__init__.py
context_handler/context.py
context_handler/ext/__init__.py
context_handler/ext/sqlalchemy/__init__.py
context_handler/ext/sqlalchemy/asyncio.py
context_handler/ext/sqlalchemy/sync.py
context_handler/interfaces/__init__.py
context_handler/interfaces/adapter.py
context_handler/main.py
context_handler/py.typed
context_handler/typedef.py
context_handler/utils/__init__.py
context_handler/utils/helpers.py
context_handler-6.0.0.dist-info/LICENSE
context_handler-6.0.0.dist-info/METADATA
context_handler-6.0.0.dist-info/WHEEL
context_handler-6.0.0.dist-info/RECORD
